komet/__init__.py
komet/singleton.py
komet/tail.py
komet/version.py
tests/__init__.py
tests/instances.py
tests/test_singleton.py
komet-0.3.0.dist-info/LICENSE
komet-0.3.0.dist-info/METADATA
komet-0.3.0.dist-info/WHEEL
komet-0.3.0.dist-info/top_level.txt
komet-0.3.0.dist-info/RECORD
